[
    {
        "inputs":  [
                       {
                           "internalType":  "address",
                           "name":  "initialOwner",
                           "type":  "address"
                       }
                   ],
        "stateMutability":  "nonpayable",
        "type":  "constructor"
    },
    {
        "inputs":  [
                       {
                           "internalType":  "address",
                           "name":  "owner",
                           "type":  "address"
                       }
                   ],
        "name":  "OwnableInvalidOwner",
        "type":  "error"
    },
    {
        "inputs":  [
                       {
                           "internalType":  "address",
                           "name":  "account",
                           "type":  "address"
                       }
                   ],
        "name":  "OwnableUnauthorizedAccount",
        "type":  "error"
    },
    {
        "anonymous":  false,
        "inputs":  [
                       {
                           "indexed":  true,
                           "internalType":  "address",
                           "name":  "wallet",
                           "type":  "address"
                       },
                       {
                           "indexed":  false,
                           "internalType":  "string",
                           "name":  "reason",
                           "type":  "string"
                       }
                   ],
        "name":  "AddressBlacklisted",
        "type":  "event"
    },
    {
        "anonymous":  false,
        "inputs":  [
                       {
                           "indexed":  true,
                           "internalType":  "address",
                           "name":  "wallet",
                           "type":  "address"
                       }
                   ],
        "name":  "AddressUnblacklisted",
        "type":  "event"
    },
    {
        "anonymous":  false,
        "inputs":  [
                       {
                           "indexed":  true,
                           "internalType":  "address",
                           "name":  "contractAddr",
                           "type":  "address"
                       },
                       {
                           "indexed":  false,
                           "internalType":  "bool",
                           "name":  "status",
                           "type":  "bool"
                       }
                   ],
        "name":  "AuthorizedContractChanged",
        "type":  "event"
    },
    {
        "anonymous":  false,
        "inputs":  [
                       {
                           "indexed":  true,
                           "internalType":  "address",
                           "name":  "wallet",
                           "type":  "address"
                       },
                       {
                           "indexed":  false,
                           "internalType":  "bytes32",
                           "name":  "kycHash",
                           "type":  "bytes32"
                       },
                       {
                           "indexed":  false,
                           "internalType":  "string",
                           "name":  "role",
                           "type":  "string"
                       }
                   ],
        "name":  "IdentityRegistered",
        "type":  "event"
    },
    {
        "anonymous":  false,
        "inputs":  [
                       {
                           "indexed":  true,
                           "internalType":  "address",
                           "name":  "wallet",
                           "type":  "address"
                       },
                       {
                           "indexed":  true,
                           "internalType":  "address",
                           "name":  "rejectedBy",
                           "type":  "address"
                       },
                       {
                           "indexed":  false,
                           "internalType":  "string",
                           "name":  "reason",
                           "type":  "string"
                       }
                   ],
        "name":  "IdentityRejected",
        "type":  "event"
    },
    {
        "anonymous":  false,
        "inputs":  [
                       {
                           "indexed":  true,
                           "internalType":  "address",
                           "name":  "wallet",
                           "type":  "address"
                       },
                       {
                           "indexed":  true,
                           "internalType":  "address",
                           "name":  "verifiedBy",
                           "type":  "address"
                       }
                   ],
        "name":  "IdentityVerified",
        "type":  "event"
    },
    {
        "anonymous":  false,
        "inputs":  [
                       {
                           "indexed":  true,
                           "internalType":  "address",
                           "name":  "wallet",
                           "type":  "address"
                       },
                       {
                           "indexed":  false,
                           "internalType":  "bool",
                           "name":  "status",
                           "type":  "bool"
                       }
                   ],
        "name":  "OfficerStatusChanged",
        "type":  "event"
    },
    {
        "anonymous":  false,
        "inputs":  [
                       {
                           "indexed":  true,
                           "internalType":  "address",
                           "name":  "previousOwner",
                           "type":  "address"
                       },
                       {
                           "indexed":  true,
                           "internalType":  "address",
                           "name":  "newOwner",
                           "type":  "address"
                       }
                   ],
        "name":  "OwnershipTransferred",
        "type":  "event"
    },
    {
        "inputs":  [
                       {
                           "internalType":  "address",
                           "name":  "",
                           "type":  "address"
                       }
                   ],
        "name":  "authorizedContracts",
        "outputs":  [
                        {
                            "internalType":  "bool",
                            "name":  "",
                            "type":  "bool"
                        }
                    ],
        "stateMutability":  "view",
        "type":  "function"
    },
    {
        "inputs":  [
                       {
                           "internalType":  "address",
                           "name":  "wallet",
                           "type":  "address"
                       },
                       {
                           "internalType":  "string",
                           "name":  "reason",
                           "type":  "string"
                       }
                   ],
        "name":  "blacklistAddress",
        "outputs":  [

                    ],
        "stateMutability":  "nonpayable",
        "type":  "function"
    },
    {
        "inputs":  [
                       {
                           "internalType":  "address",
                           "name":  "",
                           "type":  "address"
                       }
                   ],
        "name":  "blacklisted",
        "outputs":  [
                        {
                            "internalType":  "bool",
                            "name":  "",
                            "type":  "bool"
                        }
                    ],
        "stateMutability":  "view",
        "type":  "function"
    },
    {
        "inputs":  [
                       {
                           "internalType":  "address",
                           "name":  "wallet",
                           "type":  "address"
                       }
                   ],
        "name":  "getIdentity",
        "outputs":  [
                        {
                            "components":  [
                                               {
                                                   "internalType":  "bytes32",
                                                   "name":  "kycHash",
                                                   "type":  "bytes32"
                                               },
                                               {
                                                   "internalType":  "enum IdentityRegistry.KYCStatus",
                                                   "name":  "status",
                                                   "type":  "uint8"
                                               },
                                               {
                                                   "internalType":  "uint256",
                                                   "name":  "registeredAt",
                                                   "type":  "uint256"
                                               },
                                               {
                                                   "internalType":  "string",
                                                   "name":  "role",
                                                   "type":  "string"
                                               }
                                           ],
                            "internalType":  "struct IdentityRegistry.Identity",
                            "name":  "",
                            "type":  "tuple"
                        }
                    ],
        "stateMutability":  "view",
        "type":  "function"
    },
    {
        "inputs":  [
                       {
                           "internalType":  "address",
                           "name":  "",
                           "type":  "address"
                       }
                   ],
        "name":  "identities",
        "outputs":  [
                        {
                            "internalType":  "bytes32",
                            "name":  "kycHash",
                            "type":  "bytes32"
                        },
                        {
                            "internalType":  "enum IdentityRegistry.KYCStatus",
                            "name":  "status",
                            "type":  "uint8"
                        },
                        {
                            "internalType":  "uint256",
                            "name":  "registeredAt",
                            "type":  "uint256"
                        },
                        {
                            "internalType":  "string",
                            "name":  "role",
                            "type":  "string"
                        }
                    ],
        "stateMutability":  "view",
        "type":  "function"
    },
    {
        "inputs":  [
                       {
                           "internalType":  "address",
                           "name":  "",
                           "type":  "address"
                       }
                   ],
        "name":  "isOfficer",
        "outputs":  [
                        {
                            "internalType":  "bool",
                            "name":  "",
                            "type":  "bool"
                        }
                    ],
        "stateMutability":  "view",
        "type":  "function"
    },
    {
        "inputs":  [
                       {
                           "internalType":  "address",
                           "name":  "wallet",
                           "type":  "address"
                       }
                   ],
        "name":  "isVerified",
        "outputs":  [
                        {
                            "internalType":  "bool",
                            "name":  "",
                            "type":  "bool"
                        }
                    ],
        "stateMutability":  "view",
        "type":  "function"
    },
    {
        "inputs":  [

                   ],
        "name":  "owner",
        "outputs":  [
                        {
                            "internalType":  "address",
                            "name":  "",
                            "type":  "address"
                        }
                    ],
        "stateMutability":  "view",
        "type":  "function"
    },
    {
        "inputs":  [
                       {
                           "internalType":  "address",
                           "name":  "wallet",
                           "type":  "address"
                       },
                       {
                           "internalType":  "bytes32",
                           "name":  "kycHash",
                           "type":  "bytes32"
                       },
                       {
                           "internalType":  "string",
                           "name":  "role",
                           "type":  "string"
                       }
                   ],
        "name":  "registerIdentity",
        "outputs":  [

                    ],
        "stateMutability":  "nonpayable",
        "type":  "function"
    },
    {
        "inputs":  [
                       {
                           "internalType":  "address",
                           "name":  "wallet",
                           "type":  "address"
                       },
                       {
                           "internalType":  "string",
                           "name":  "reason",
                           "type":  "string"
                       }
                   ],
        "name":  "rejectIdentity",
        "outputs":  [

                    ],
        "stateMutability":  "nonpayable",
        "type":  "function"
    },
    {
        "inputs":  [

                   ],
        "name":  "renounceOwnership",
        "outputs":  [

                    ],
        "stateMutability":  "nonpayable",
        "type":  "function"
    },
    {
        "inputs":  [
                       {
                           "internalType":  "address",
                           "name":  "contractAddr",
                           "type":  "address"
                       },
                       {
                           "internalType":  "bool",
                           "name":  "status",
                           "type":  "bool"
                       }
                   ],
        "name":  "setAuthorizedContract",
        "outputs":  [

                    ],
        "stateMutability":  "nonpayable",
        "type":  "function"
    },
    {
        "inputs":  [
                       {
                           "internalType":  "address",
                           "name":  "wallet",
                           "type":  "address"
                       },
                       {
                           "internalType":  "bool",
                           "name":  "status",
                           "type":  "bool"
                       }
                   ],
        "name":  "setOfficer",
        "outputs":  [

                    ],
        "stateMutability":  "nonpayable",
        "type":  "function"
    },
    {
        "inputs":  [
                       {
                           "internalType":  "address",
                           "name":  "newOwner",
                           "type":  "address"
                       }
                   ],
        "name":  "transferOwnership",
        "outputs":  [

                    ],
        "stateMutability":  "nonpayable",
        "type":  "function"
    },
    {
        "inputs":  [
                       {
                           "internalType":  "address",
                           "name":  "wallet",
                           "type":  "address"
                       }
                   ],
        "name":  "unblacklistAddress",
        "outputs":  [

                    ],
        "stateMutability":  "nonpayable",
        "type":  "function"
    },
    {
        "inputs":  [
                       {
                           "internalType":  "address",
                           "name":  "wallet",
                           "type":  "address"
                       }
                   ],
        "name":  "verifyIdentity",
        "outputs":  [

                    ],
        "stateMutability":  "nonpayable",
        "type":  "function"
    }
]
